{
    "numOptional":1,
    "requiredCore":[
        {"courseName":"CS 6304", "courseDescription":"Computer Architecture"},
        {"courseName":"CS 6363", "courseDescription":"Design and Analysis of Computer Algorithms"},
        {"courseName":"CS 6378", "courseDescription":"Advanced Operating Systems"},
        {"courseName":"CS 6396", "courseDescription":"Real-Time Systems"}
    ],
    "optionalCore":[
        {"courseName":"CS 6349", "courseDescription":"Network Security"},
        {"courseName":"CS 6376", "courseDescription":"Parallel Processing"},
        {"courseName":"CS 6380", "courseDescription":"Distributed Computing"},
        {"courseName":"CS 6397", "courseDescription":"Synthesis and Opt. of High-Perf. Systems"},
        {"courseName":"CS 6399", "courseDescription":"Parallel Architectures and Systems"}
],
    "admissionPrerequisites":[
        {"courseName":"CS 5303", "courseDescription":"Computer Science I"},
        {"courseName":"CS 5330", "courseDescription":"Computer Science II"},
        {"courseName":"CS 5333", "courseDescription":"Discrete Structures"},
        {"courseName":"CS 5343", "courseDescription":"Algorithm Analysis & Data Structures"},
        {"courseName":"CS 5348", "courseDescription":"Operating System Concepts"},
        {"courseName":"CS 5390", "courseDescription":"Computer Networks"}
    ]
}